jarvis_STT/_init_.py
GOPIRAJ_STT-0.1.dist-info/METADATA
GOPIRAJ_STT-0.1.dist-info/WHEEL
GOPIRAJ_STT-0.1.dist-info/top_level.txt
GOPIRAJ_STT-0.1.dist-info/RECORD
