Metadata-Version: 2.1
Name: GOPIRAJ-STT
Version: 0.1
Summary: this is a speech to text package created by Gopi Raj
Author: Gopi Raj
